{
  "chainName": "spike",
  "title": "Spike Block Explorer",
  "extra": {
    "profile": true,
    "graphqlWs": true
  },
  "previewImage": "https://s3.bigdipper.live/cosmoshub.png",
  "themes": {
    "default": "light",
    "themeList": ["dark", "light", "deuteranopia", "tritanopia"],
    "dark": {
      "primary": {
        "main": "#6B9EFF",
        "contrastText": "#FFFFFF"
      },
      "background": {
        "default": "#020202",
        "paper": "#191B26"
      },
      "divider": "#363A51",
      "text": {
        "primary": "#E6E6E6",
        "secondary": "#C4C4C4"
      },
      "custom": {
        "general": {
          "background": "#020202",
          "surfaceOne": "#191B26",
          "surfaceTwo": "#282A36",
          "icon": "#999999"
        },
        "fonts": {
          "fontOne": "#E6E6E6",
          "fontTwo": "#C4C4C4",
          "fontThree": "#818181",
          "fontFour": "#999999",
          "fontFive": "#FFFFFF",
          "highlight": "#6AA6FF"
        },
        "primaryData": {
          "one": "#AE73F8",
          "two": "#6B9EFF",
          "three": "#5ACF78",
          "four": "#E3AB55"
        },
        "results": {
          "pass": "#1EC490",
          "fail": "#FD3B4C"
        },
        "tokenomics": {
          "one": "#5E94FF",
          "two": "#E3AB55",
          "three": "#5ACF78"
        },
        "condition": {
          "zero": "#E8E8E8",
          "one": "#1EC490",
          "two": "#FF961B",
          "three": "#FC6A8A"
        },
        "charts": {
          "zero": "#E8E8E8",
          "one": "#5ACF78",
          "two": "#5ACF78",
          "three": "#AE73F8",
          "four": "#5E94FF",
          "five": "#C25396"
        },
        "tags": {
          "zero": "#E8E8E8",
          "one": "#2460FA",
          "two": "#2BA891",
          "three": "#E79720",
          "four": "#F17047",
          "five": "#DA4B4B",
          "six": "#9438DC",
          "seven": "#1A869D",
          "eight": "#2C9944",
          "nine": "#B49F31",
          "ten": "#E9A846",
          "eleven": "#E94681",
          "twelve": "#C15EC4",
          "thirteen": "#C388D9",
          "fourteen": "#46AEE9",
          "fifteen": "#58BC91",
          "sixteen": "#90BC58",
          "seventeen": "#E99E8E",
          "eighteen": "#F0A479",
          "nineteen": "#D37763",
          "twenty": "#D9C788"
        }
      }
    },
    "light": {
      "primary": {
        "main": "#6B9EFF",
        "contrastText": "#FFFFFF"
      },
      "background": {
        "default": "#F7F7FF",
        "paper": "#FFFFFF"
      },
      "divider": "#707070",
      "text": {
        "primary": "#000000",
        "secondary": "#414141"
      },
      "custom": {
        "general": {
          "background": "#F7F7FF",
          "surfaceOne": "#FFFFFF",
          "surfaceTwo": "#EFEFEF",
          "icon": "#999999"
        },
        "fonts": {
          "fontOne": "#000000",
          "fontTwo": "#414141",
          "fontThree": "#777777",
          "fontFour": "#999999",
          "fontFive": "#FFFFFF",
          "highlight": "#6AA6FF"
        },
        "primaryData": {
          "one": "#AE73F8",
          "two": "#6B9EFF",
          "three": "#5ACF78",
          "four": "#E3AB55"
        },
        "results": {
          "pass": "#1EC490",
          "fail": "#FD3B4C"
        },
        "tokenomics": {
          "one": "#5E94FF",
          "two": "#E3AB55",
          "three": "#5ACF78"
        },
        "condition": {
          "zero": "#E8E8E8",
          "one": "#1EC490",
          "two": "#FF961B",
          "three": "#FC6A8A"
        },
        "charts": {
          "zero": "#E8E8E8",
          "one": "#5ACF78",
          "two": "#5ACF78",
          "three": "#AE73F8",
          "four": "#5E94FF",
          "five": "#C25396"
        },
        "tags": {
          "zero": "#E8E8E8",
          "one": "#2460FA",
          "two": "#2BA891",
          "three": "#E79720",
          "four": "#F17047",
          "five": "#DA4B4B",
          "six": "#9438DC",
          "seven": "#1A869D",
          "eight": "#2C9944",
          "nine": "#B49F31",
          "ten": "#E9A846",
          "eleven": "#E94681",
          "twelve": "#C15EC4",
          "thirteen": "#C388D9",
          "fourteen": "#46AEE9",
          "fifteen": "#58BC91",
          "sixteen": "#90BC58",
          "seventeen": "#E99E8E",
          "eighteen": "#F0A479",
          "nineteen": "#D37763",
          "twenty": "#D9C788"
        }
      }
    }
  },
  "chains": [
    {
      "network": "spike-testnet",
      "chainType": "Testnet",
      "genesis": {
        "time": "2021-07-13T08:00:00",
        "height": 1
      },
      "prefix": {
        "consensus": "spikevalcons",
        "validator": "spikevaloper",
        "account": "spike"
      },
      "primaryTokenUnit": "uspk",
      "votingPowerTokenUnit": "uspk",
      "tokenUnits": {
        "uspk": {
          "display": "spk",
          "exponent": 6
        }
      },
      "endpoints": {
        "graphql": "http://chris.dag.fan:8080/v1/graphql",
        "graphqlWebsocket": "ws://chris.dag.fan:8080/v1/graphql",
        "publicRpcWebsocket": "ws://centos.dag.fan:26657/websocket"
      },
      "marketing": {
        "matomoURL": "",
        "matomoSiteID": ""
      }
    }
  ]
}
